parkplus_global_utils/__init__.py
parkplus_global_utils/authentication/__init__.py
parkplus_global_utils/authentication/auth_details.py
parkplus_global_utils/authentication/config.py
parkplus_global_utils/authentication/raise_exception.py
parkplus_global_utils/authentication/token_utils.py
parkplus_global_utils/authentication/user_details.py
parkplus_global_utils/authentication/utils.py
parkplus_global_utils/cities/__init__.py
parkplus_global_utils/cities/constants.py
parkplus_global_utils/cities/utils.py
parkplus_global_utils/db/__init__.py
parkplus_global_utils/db/abs_orm_db.py
parkplus_global_utils/db/app_logger.py
parkplus_global_utils/db/basic_utils.py
parkplus_global_utils/db/crud_manager.py
pramod_test_utils-0.0.63.dist-info/METADATA
pramod_test_utils-0.0.63.dist-info/WHEEL
pramod_test_utils-0.0.63.dist-info/top_level.txt
pramod_test_utils-0.0.63.dist-info/RECORD
