Metadata-Version: 2.1
Name: pramod-test-utils
Version: 0.0.63
Summary: Reusable global utils
Home-page: UNKNOWN
Author: Utils Team
License: UNKNOWN
Platform: UNKNOWN
Classifier: Programming Language :: Python :: 3
Classifier: License :: OSI Approved :: BSD License
Classifier: Operating System :: OS Independent
Requires-Dist: PyJWT (==1.7.1)
